milan/__init__.py
milanvarghese-0.0.2.dist-info/LICENSE.txt
milanvarghese-0.0.2.dist-info/METADATA
milanvarghese-0.0.2.dist-info/WHEEL
milanvarghese-0.0.2.dist-info/top_level.txt
milanvarghese-0.0.2.dist-info/RECORD
