Metadata-Version: 2.1
Name: milanvarghese
Version: 0.0.2
Summary: My First Python Package
Home-page: https://github.com/pypa/sampleproject
Author: Milan Varghese
Author-email: milanvarghese99@gmail.com
License: UNKNOWN
Platform: UNKNOWN
Classifier: Programming Language :: Python :: 3
Classifier: License :: OSI Approved :: MIT License
Classifier: Operating System :: OS Independent
Requires-Python: >=3.6
